carapis/__init__.py
carapis/client.py
carapis/exceptions.py
carapis/models.py
carapis/py.typed
carapis/types.py
carapis/generated/__init__.py
carapis/generated/vehicles_api/__init__.py
carapis/generated/vehicles_api/pyproject.toml
carapis/generated/vehicles_api/django_revolution_vehicles_api/__init__.py
carapis/generated/vehicles_api/django_revolution_vehicles_api/client.py
carapis/generated/vehicles_api/django_revolution_vehicles_api/errors.py
carapis/generated/vehicles_api/django_revolution_vehicles_api/py.typed
carapis/generated/vehicles_api/django_revolution_vehicles_api/types.py
carapis/generated/vehicles_api/django_revolution_vehicles_api/api/__init__.py
carapis/generated/vehicles_api/django_revolution_vehicles_api/api/vehicles_api/__init__.py
carapis/generated/vehicles_api/django_revolution_vehicles_api/api/vehicles_api/vehicles_api_image_retrieve.py
carapis/generated/vehicles_api/django_revolution_vehicles_api/api/vehicles_api/vehicles_api_v1_brands_cache_info_retrieve.py
carapis/generated/vehicles_api/django_revolution_vehicles_api/api/vehicles_api/vehicles_api_v1_brands_list.py
carapis/generated/vehicles_api/django_revolution_vehicles_api/api/vehicles_api/vehicles_api_v1_brands_models_cache_info_retrieve.py
carapis/generated/vehicles_api/django_revolution_vehicles_api/api/vehicles_api/vehicles_api_v1_brands_models_list.py
carapis/generated/vehicles_api/django_revolution_vehicles_api/api/vehicles_api/vehicles_api_v1_brands_models_retrieve.py
carapis/generated/vehicles_api/django_revolution_vehicles_api/api/vehicles_api/vehicles_api_v1_brands_models_vehicles_cache_info_retrieve.py
carapis/generated/vehicles_api/django_revolution_vehicles_api/api/vehicles_api/vehicles_api_v1_brands_models_vehicles_list.py
carapis/generated/vehicles_api/django_revolution_vehicles_api/api/vehicles_api/vehicles_api_v1_brands_models_vehicles_retrieve.py
carapis/generated/vehicles_api/django_revolution_vehicles_api/api/vehicles_api/vehicles_api_v1_brands_retrieve.py
carapis_api-2.0.4.dist-info/METADATA
carapis_api-2.0.4.dist-info/WHEEL
carapis_api-2.0.4.dist-info/top_level.txt
carapis_api-2.0.4.dist-info/RECORD
