Metadata-Version: 2.4
Name: carapis-api
Version: 2.0.4
Summary: Universal Python client for CARAPIS Vehicles API - Access automotive data from 25+ global marketplaces including Cars.com, AutoScout24, Encar, Auto.ru, and more. Enterprise-grade automotive data extraction with real-time vehicle listings, pricing, and market intelligence.
Author-email: CARAPIS Team <info@carapis.com>
Maintainer-email: CARAPIS Team <info@carapis.com>
License: MIT
Project-URL: Homepage, https://carapis.com
Project-URL: Documentation, https://docs.carapis.com
Project-URL: Funding, https://carapis.com/pricing
Keywords: automotive,vehicles,cars,api,client,python,carapis,automotive-data,vehicle-listings,car-marketplace,automotive-api,cars.com,autoscout24,encar,auto.ru,automotive-scraping,vehicle-data,car-data,marketplace-api,automotive-intelligence,vehicle-search,car-pricing,automotive-analytics,dealership-tools,automotive-platform,vehicle-inventory,car-market-data,automotive-insights,real-time-data,enterprise-api,ssr,django,fastapi,flask,async,asyncio
Classifier: Development Status :: 5 - Production/Stable
Classifier: Intended Audience :: Developers
Classifier: Intended Audience :: Financial and Insurance Industry
Classifier: Intended Audience :: Information Technology
Classifier: License :: OSI Approved :: MIT License
Classifier: Operating System :: OS Independent
Classifier: Programming Language :: Python :: 3
Classifier: Programming Language :: Python :: 3.8
Classifier: Programming Language :: Python :: 3.9
Classifier: Programming Language :: Python :: 3.10
Classifier: Programming Language :: Python :: 3.11
Classifier: Programming Language :: Python :: 3.12
Classifier: Topic :: Internet :: WWW/HTTP :: Dynamic Content
Classifier: Topic :: Office/Business :: Financial
Classifier: Topic :: Scientific/Engineering :: Information Analysis
Classifier: Topic :: Software Development :: Libraries :: Python Modules
Classifier: Topic :: System :: Networking
Classifier: Typing :: Typed
Requires-Python: >=3.8
Requires-Dist: httpx>=0.24.0
Requires-Dist: attrs>=21.3.0
Requires-Dist: python-dateutil>=2.8.0
Provides-Extra: dev
Requires-Dist: pytest>=7.0.0; extra == "dev"
Requires-Dist: pytest-asyncio>=0.21.0; extra == "dev"
Requires-Dist: pytest-cov>=4.0.0; extra == "dev"
Requires-Dist: black>=23.0.0; extra == "dev"
Requires-Dist: isort>=5.12.0; extra == "dev"
Requires-Dist: flake8>=6.0.0; extra == "dev"
Requires-Dist: mypy>=1.0.0; extra == "dev"
Requires-Dist: pre-commit>=3.0.0; extra == "dev"
Requires-Dist: tomlkit>=0.12.0; extra == "dev"
Requires-Dist: rich>=13.0.0; extra == "dev"
Requires-Dist: questionary>=2.0.0; extra == "dev"
Requires-Dist: build>=1.0.0; extra == "dev"
Requires-Dist: twine>=4.0.0; extra == "dev"
Provides-Extra: docs
Requires-Dist: mkdocs>=1.4.0; extra == "docs"
Requires-Dist: mkdocs-material>=9.0.0; extra == "docs"
Requires-Dist: mkdocstrings[python]>=0.20.0; extra == "docs"
Provides-Extra: test
Requires-Dist: pytest>=7.0.0; extra == "test"
Requires-Dist: pytest-asyncio>=0.21.0; extra == "test"
Requires-Dist: pytest-cov>=4.0.0; extra == "test"
Requires-Dist: httpx[testing]>=0.24.0; extra == "test"
